cuber/__init__.py
cuber/interface.py
cuber/actuator/__init__.py
cuber/actuator/actuator_meta.py
cuber/actuator/actuator_realization.py
cuber/doc/README.mdown
cuber/manager/__init__.py
cuber/manager/dispatch.py
cuber/manager/graph.py
cuber/model/__init__.py
cuber/model/data.py
cuber/model/mixin.py
cuber/runner/__init__.py
cuber/runner/daskengine.py
cuber/runner/rayengine.py
cuber/test/cuber_config.yaml
cuber/test/test_actuator.py
cuber/test/test_config.py
cuber/test/test_controller.py
cuber/test/test_datamodel.py
cuber/test/test_decorator.py
cuber/test/test_execute.py
cuber/test/test_interface.py
cuber/test/test_main.py
cuber/test/test_networkx.py
cuber/test/test_ray.py
cuber/test/test_scheduler.py
cuber/test/test_tmp.py
cuber/test/test_transmission.py
cuber/tool/__init__.py
cuber/tool/information.py
cuber/tool/state.py
shihua_cuber-0.1.dist-info/LICENSE
shihua_cuber-0.1.dist-info/METADATA
shihua_cuber-0.1.dist-info/WHEEL
shihua_cuber-0.1.dist-info/top_level.txt
shihua_cuber-0.1.dist-info/RECORD
