Metadata-Version: 2.1
Name: shihua-cuber
Version: 0.1
Summary: Cuber is an ensemble learning frame tool.
Home-page: https://github.com/redblue0216/Cuber
Author: shihua
Author-email: 15021408795@163.com
License: MIT
Platform: UNKNOWN
Requires-Python: >=3.9.12
License-File: LICENSE
